mopidy_cd/__init__.py
mopidy_cd/backend.py
mopidy_cd/cdrom.py
mopidy_cd/ext.conf
Mopidy_Cd-0.5.dist-info/LICENSE
Mopidy_Cd-0.5.dist-info/METADATA
Mopidy_Cd-0.5.dist-info/WHEEL
Mopidy_Cd-0.5.dist-info/entry_points.txt
Mopidy_Cd-0.5.dist-info/top_level.txt
Mopidy_Cd-0.5.dist-info/RECORD
