Metadata-Version: 2.1
Name: Mopidy-Cd
Version: 0.5
Summary: Mopidy extension to play audio CDs
Home-page: https://github.com/forscher21/mopidy-cd
Author: Antonio Sartori
Author-email: antonio217@web.de
License: Apache License, Version 2.0
Platform: UNKNOWN
Classifier: Environment :: No Input/Output (Daemon)
Classifier: Intended Audience :: End Users/Desktop
Classifier: License :: OSI Approved :: Apache Software License
Classifier: Operating System :: OS Independent
Classifier: Programming Language :: Python :: 2
Classifier: Topic :: Multimedia :: Sound/Audio :: Players
Requires-Dist: Mopidy (>=1.0)
Requires-Dist: Pykka (>=1.1)
Requires-Dist: musicbrainzngs (==0.6)
Requires-Dist: setuptools
